mait.py
muxmait-0.1.5.dist-info/LICENSE
muxmait-0.1.5.dist-info/METADATA
muxmait-0.1.5.dist-info/WHEEL
muxmait-0.1.5.dist-info/entry_points.txt
muxmait-0.1.5.dist-info/top_level.txt
muxmait-0.1.5.dist-info/RECORD
